wowool/build/docstrings_resolve_links.py
wowool/build/exceptions.py
wowool/build/git.py
wowool/build/logging.py
wowool/build/long_description.py
wowool/build/platform.py
wowool/build/pydist.py
wowool/build/pypi.py
wowool/build/pytask.py
wowool/build/pytest.py
wowool/build/samples.py
wowool/build/utility.py
wowool/build/docstrings/extract_docstrings.py
wowool/build/docstrings/json_to_markdown.py
wowool/build/docstrings/json_visitor.py
wowool/build/docstrings/resolve_links.py
wowool/build/docstrings/tojson.py
wowool_build-0.1.0.dist-info/METADATA
wowool_build-0.1.0.dist-info/WHEEL
wowool_build-0.1.0.dist-info/entry_points.txt
wowool_build-0.1.0.dist-info/top_level.txt
wowool_build-0.1.0.dist-info/RECORD
