Metadata-Version: 2.1
Name: wowool-build
Version: 0.1.0
Summary: Wowool Build System
Home-page: https://www.wowool.com/
Author: Wowool
Author-email: info@wowool.com
Requires-Python: >=3.11
Requires-Dist: invoke
Requires-Dist: build
Requires-Dist: wheel
Requires-Dist: setuptools
Requires-Dist: setuptools-scm
Requires-Dist: docstring-parser
